{
  "B": {
    "C": "bicycle",
    "D": "bed",
    "E": "bee",
    "F": "beef",
    "G": "bag",
    "H": "bash",
    "I": "bird",
    "J": "bungee",
    "K": "book",
    "L": "bell",
    "M": "bomb",
    "N": "banana",
    "O": "bone",
    "P": "backpack",
    "Q": "bbq",
    "R": "beer",
    "S": "bass",
    "T": "bat",
    "U": "bus",
    "V": "brave",
    "W": "bow",
    "X": "box"
  },
  "C": {
    "B": "cable",
    "D": "code",
    "E": "chen",
    "F": "chief",
    "G": "cage",
    "H": "chest",
    "I": "city",
    "J": "change",
    "K": "cook",
    "L": "cloud",
    "M": "come",
    "N": "can",
    "O": "cool",
    "P": "cop",
    "Q": "check",
    "R": "chair",
    "S": "cash",
    "T": "cat",
    "U": "chew",
    "V": "cave",
    "W": "cow",
    "X": "castel"
  },
  "D": {
    "B": "debt",
    "C": "deck",
    "E": "dead",
    "F": "dolphin",
    "G": "dog",
    "H": "doughnut",
    "I": "die",
    "J": "dj",
    "K": "dark",
    "L": "drill",
    "M": "doom",
    "N": "deny",
    "O": "door",
    "P": "deepen",
    "Q": "drug",
    "R": "dress",
    "S": "dinosaur",
    "T": "dot",
    "U": "duck",
    "V": "drive",
    "W": "draw",
    "X": "dracossack"
  },
  "E": {
    "B": "eyeball",
    "C": "eclipse",
    "D": "edge",
    "F": "effect",
    "G": "egg",
    "H": "elight",
    "I": "eskimo",
    "J": "eject",
    "K": "earthquake",
    "L": "eel",
    "M": "emperor",
    "N": "envelop",
    "O": "ebook",
    "P": "elephant",
    "Q": "equation",
    "R": "eraser",
    "S": "yes",
    "T": "eat",
    "U": "europe",
    "V": "evil",
    "W": "elbow",
    "X": "excalibur"
  },
  "F": {
    "B": "football",
    "C": "face",
    "D": "food",
    "E": "feed",
    "G": "fog",
    "H": "fish",
    "I": "fight",
    "J": "fudge",
    "K": "fork",
    "L": "fly",
    "M": "farm",
    "N": "fan",
    "O": "fox",
    "P": "fap",
    "Q": "freak",
    "R": "fruit",
    "S": "fast",
    "T": "feet",
    "U": "fuck",
    "V": "five",
    "W": "flower",
    "X": "fix"
  },
  "G": {
    "B": "grab",
    "C": "grace",
    "D": "god",
    "E": "gem",
    "F": "gift",
    "H": "ghost",
    "I": "giant",
    "J": "grape",
    "K": "goku",
    "L": "glass",
    "M": "game",
    "N": "gone",
    "O": "go",
    "P": "gap",
    "Q": "greek",
    "R": "green",
    "S": "gas",
    "T": "get",
    "U": "gun",
    "V": "give",
    "W": "grow",
    "X": "galaxy"
  },
  "H": {
    "B": "habit",
    "C": "hack",
    "D": "head",
    "E": "helm",
    "F": "half",
    "G": "hug",
    "I": "he",
    "J": "hedge",
    "K": "hook",
    "L": "hell",
    "M": "hammer",
    "N": "honey",
    "O": "santa",
    "P": "hope",
    "Q": "hockey",
    "R": "hair",
    "S": "horse",
    "T": "hat",
    "U": "hunter",
    "V": "heaven",
    "W": "hawk",
    "X": "hex"
  },
  "I": {
    "B": "inbox",
    "C": "ice",
    "D": "idea",
    "E": "yay",
    "F": "if",
    "G": "ignite",
    "H": "ying",
    "J": "injury",
    "K": "ink",
    "L": "ill",
    "M": "aim",
    "N": "indian",
    "O": "inferno",
    "P": "ipod",
    "Q": "iraq",
    "R": "iron",
    "S": "is",
    "T": "italy",
    "U": "immune",
    "V": "ivory",
    "W": "eye",
    "X": "index"
  },
  "J": {
    "B": "jab",
    "C": "juice",
    "D": "jedi",
    "E": "jealous",
    "F": "joyfull",
    "G": "jog",
    "H": "john",
    "I": "jigsaw",
    "K": "joker",
    "L": "jelly",
    "M": "jump",
    "N": "jeans",
    "O": "joey",
    "P": "jeep",
    "Q": "joke",
    "R": "jair",
    "S": "jesus",
    "T": "jet",
    "U": "jungle",
    "V": "javalin",
    "W": "jaw",
    "X": "ajax"
  },
  "K": {
    "B": "keyboard",
    "C": "kick",
    "D": "kid",
    "E": "key",
    "F": "kfc",
    "G": "king",
    "H": "keyhole",
    "I": "kite",
    "J": "kanji",
    "L": "kill",
    "M": "kimono",
    "N": "knight",
    "O": "koala",
    "P": "keep",
    "Q": "catch",
    "R": "car",
    "S": "kiss",
    "T": "katana",
    "U": "kungfu",
    "V": "kevlar",
    "W": "kiwi",
    "X": "knob"
  },
  "L": {
    "B": "lab",
    "C": "lich",
    "D": "lead",
    "E": "leek",
    "F": "leaf",
    "G": "lego",
    "H": "clothes",
    "I": "lip",
    "J": "large",
    "K": "lock",
    "M": "lamp",
    "N": "lantern",
    "O": "loop",
    "P": "leap",
    "Q": "liquid",
    "R": "liar",
    "S": "lost",
    "T": "loot",
    "U": "lust",
    "V": "love",
    "W": "low",
    "X": "lasso"
  },
  "M": {
    "B": "mob",
    "C": "magician",
    "D": "mad",
    "E": "me",
    "F": "muffin",
    "G": "magnet",
    "H": "math",
    "I": "milk",
    "J": "major",
    "K": "monkey",
    "L": "melt",
    "N": "moon",
    "O": "mom",
    "P": "map",
    "Q": "mashed",
    "R": "mars",
    "S": "mouse",
    "T": "meet",
    "U": "mushroom",
    "V": "move",
    "W": "mower",
    "X": "max"
  },
  "N": {
    "B": "notebook",
    "C": "neck",
    "D": "nude",
    "E": "neon",
    "F": "knife",
    "G": "night",
    "H": "neighborhood",
    "I": "nazi",
    "J": "ninja",
    "K": "nuke",
    "L": "noel",
    "M": "name",
    "O": "nose",
    "P": "nipple",
    "Q": "nasdaq",
    "R": "nerd",
    "S": "nest",
    "T": "net",
    "U": "nuclear",
    "V": "navy",
    "W": "new",
    "X": "naix"
  },
  "O": {
    "B": "obelisk",
    "C": "octopus",
    "D": "odd",
    "E": "corpse",
    "F": "office",
    "G": "orge",
    "H": "other",
    "I": "oil",
    "J": "ojama",
    "K": "ok",
    "L": "old",
    "M": "monk",
    "N": "onion",
    "P": "opera",
    "Q": "mockup",
    "R": "orange",
    "S": "ostrick",
    "T": "outer",
    "U": "south",
    "V": "oven",
    "W": "owl",
    "X": "oxy"
  },
  "P": {
    "B": "public",
    "C": "pacman",
    "D": "panda",
    "E": "pay",
    "F": "perfurm",
    "G": "pig",
    "H": "pharaoh",
    "I": "pie",
    "J": "pijama",
    "K": "pick",
    "L": "pilot",
    "M": "palm",
    "N": "pen",
    "O": "pop",
    "Q": "path",
    "R": "poor",
    "S": "piss",
    "T": "pet",
    "U": "push",
    "V": "prevent",
    "W": "power",
    "X": "pixel"
  },
  "Q": {
    "B": "throb",
    "C": "quick",
    "D": "squad",
    "E": "queue",
    "F": "thief",
    "G": "thigh",
    "H": "don-quixote",
    "I": "quiet",
    "J": "quiz",
    "K": "quark",
    "L": "quill",
    "M": "them",
    "N": "then",
    "O": "comet",
    "P": "equip",
    "R": "quarry",
    "S": "question",
    "T": "quit",
    "U": "queen",
    "V": "quiver",
    "W": "qwerty",
    "X": "quicksand"
  },
  "R": {
    "B": "rabit",
    "C": "rack",
    "D": "red",
    "E": "reply",
    "F": "roof",
    "G": "ring",
    "H": "recharge",
    "I": "rice",
    "J": "reject",
    "K": "rock",
    "L": "rail",
    "M": "ram",
    "N": "range",
    "O": "rope",
    "P": "rape",
    "Q": "rocket",
    "S": "rust",
    "T": "rat",
    "U": "ruby",
    "V": "raven",
    "W": "row",
    "X": "t-rex"
  },
  "S": {
    "B": "sub",
    "C": "sock",
    "D": "sad",
    "E": "sea",
    "F": "soft",
    "G": "sing",
    "H": "shoe",
    "I": "sink",
    "J": "judge",
    "K": "skeleton",
    "L": "smile",
    "M": "smoke",
    "N": "sand",
    "O": "soap",
    "P": "ship",
    "Q": "squirrel",
    "R": "seer",
    "T": "star",
    "U": "sun",
    "V": "save",
    "W": "swing",
    "X": "sex"
  },
  "T": {
    "B": "tab",
    "C": "touch",
    "D": "toad",
    "E": "tent",
    "F": "transform",
    "G": "tiger",
    "H": "thor",
    "I": "tire",
    "J": "trojan",
    "K": "truck",
    "L": "troll",
    "M": "team",
    "N": "teen",
    "O": "toe",
    "P": "tape",
    "Q": "teeth",
    "R": "tree",
    "S": "toss",
    "U": "tub",
    "V": "tv",
    "W": "tower",
    "X": "text"
  },
  "U": {
    "B": "urban",
    "C": "unicorn",
    "D": "under",
    "E": "uncle",
    "F": "ufo",
    "G": "ugly",
    "H": "frankenstein",
    "I": "suit",
    "J": "sushi",
    "K": "uk",
    "L": "ukelele",
    "M": "umbrella",
    "N": "unite",
    "O": "uno",
    "P": "up",
    "Q": "unique",
    "R": "hurt",
    "S": "zeus",
    "T": "utopia",
    "V": "hoverboard",
    "W": "underwear",
    "X": "tuxedo"
  },
  "V": {
    "B": "vibrate",
    "C": "vacuum",
    "D": "video",
    "E": "venom",
    "F": "viper",
    "G": "vegetable",
    "H": "vehicle",
    "I": "vision",
    "J": "vengence",
    "K": "viking",
    "L": "volleyball",
    "M": "vamp",
    "N": "violin",
    "O": "volcano",
    "P": "vampire",
    "Q": "evacuation",
    "R": "virus",
    "S": "vase",
    "T": "vault",
    "U": "vulture",
    "W": "view",
    "X": "vortex"
  },
  "W": {
    "B": "web",
    "C": "witch",
    "D": "weed",
    "E": "weigh",
    "F": "waterfall",
    "G": "wing",
    "H": "wheat",
    "I": "wine",
    "J": "waterjet",
    "K": "wake",
    "L": "wall",
    "M": "warm",
    "N": "window",
    "O": "wolf",
    "P": "weapon",
    "Q": "watch",
    "R": "war",
    "S": "walrus",
    "T": "water",
    "U": "wound",
    "V": "weaver",
    "X": "wax"
  },
  "X": {
    "B": "beast",
    "C": "cyclop",
    "D": "shed",
    "E": "axe",
    "F": "safe",
    "G": "gambit",
    "H": "helicopter",
    "I": "she",
    "J": "xylophone",
    "K": "shake",
    "L": "shell",
    "M": "magneto",
    "N": "extent",
    "O": "caro",
    "P": "python",
    "Q": "quasar",
    "R": "x-ray",
    "S": "spiderman",
    "T": "terminator",
    "U": "summer",
    "V": "xavier",
    "W": "wolverine"
  }
}
